isim/__init__.py
isim/base_types.py
isim/device.py
isim/device_pair.py
isim/device_type.py
isim/runtime.py
isim-16.2.0.dist-info/LICENSE.txt
isim-16.2.0.dist-info/METADATA
isim-16.2.0.dist-info/WHEEL
isim-16.2.0.dist-info/RECORD
