Metadata-Version: 2.1
Name: isim
Version: 16.2.0
Summary: Python wrapper around the simctl utility
Home-page: https://github.com/dalemyers/xcrun
License: MIT
Keywords: xcode,xcrun,simctl,ios,simulator,isim
Author: Dale Myers
Author-email: dale@myers.io
Requires-Python: >=3.11,<4.0
Classifier: Development Status :: 5 - Production/Stable
Classifier: Environment :: MacOS X
Classifier: Intended Audience :: Developers
Classifier: License :: OSI Approved :: MIT License
Classifier: Operating System :: MacOS :: MacOS X
Classifier: Programming Language :: Python :: 3
Classifier: Programming Language :: Python :: 3.11
Classifier: Programming Language :: Python :: 3.12
Classifier: Programming Language :: Python :: 3.13
Classifier: Programming Language :: Python :: 3.10
Classifier: Programming Language :: Python :: 3.7
Classifier: Programming Language :: Python :: 3.8
Classifier: Programming Language :: Python :: 3.9
Classifier: Topic :: Software Development :: Build Tools
Classifier: Topic :: Software Development :: Testing
Classifier: Topic :: Utilities
Project-URL: Repository, https://github.com/dalemyers/xcrun
